co_datascientist/__init__.py
co_datascientist/cli.py
co_datascientist/co_datascientist_api.py
co_datascientist/docker_generator.py
co_datascientist/environment_detector.py
co_datascientist/kpi_extractor.py
co_datascientist/mcp_local_server.py
co_datascientist/models.py
co_datascientist/project_packager.py
co_datascientist/qa_cache.py
co_datascientist/run_name_generator.py
co_datascientist/settings.py
co_datascientist/user_steering.py
co_datascientist/workflow_runner.py
co_datascientist/cloud_utils/databricks_utils.py
co_datascientist/executors/AWS_executer.py
co_datascientist/executors/__init__.py
co_datascientist/executors/base_executor.py
co_datascientist/executors/databricks_executor.py
co_datascientist/executors/executor_factory.py
co_datascientist/executors/gcloud_executor.py
co_datascientist/executors/local_executor.py
co_datascientist/plotting/plot_kpi_progression.py
co_datascientist/plotting/python_diff_pdf_simple.py
tropiflo-1.0.8.dist-info/METADATA
tropiflo-1.0.8.dist-info/WHEEL
tropiflo-1.0.8.dist-info/entry_points.txt
tropiflo-1.0.8.dist-info/licenses/LICENSE
tropiflo-1.0.8.dist-info/RECORD
