Metadata-Version: 2.4
Name: tropiflo
Version: 1.0.8
Summary: A tool for agentic recursive model improvement
Project-URL: Homepage, https://github.com/TropiFloAI/co-datascientist
Project-URL: Issues, https://github.com/TropiFloAI/co-datascientist/issues
Author-email: David Gedalevich <davidgdalevich7@gmail.com>, Oz Kilim <oz.kilim@tropiflo.io>
License: Copyright (c) 2018 The Python Packaging Authority
License-File: LICENSE
Requires-Python: >=3.12
Requires-Dist: click>=8.1.8
Requires-Dist: fastmcp>=2.2.5
Requires-Dist: httpx>=0.28.1
Requires-Dist: ipdb>=0.13.13
Requires-Dist: keyring>=25.6.0
Requires-Dist: keyrings-alt>=5.0.0
Requires-Dist: matplotlib>=3.0.0
Requires-Dist: pydantic-settings>=2.9.1
Requires-Dist: python-dotenv>=1.0.0
Requires-Dist: pyyaml>=6.0.0
Requires-Dist: reportlab>=4.0.0
Requires-Dist: rich>=13.0.0
Requires-Dist: yaspin>=3.1.0
